winConnect/WinConnectBase.py
winConnect/WinConnectClient.py
winConnect/WinConnectDaemon.py
winConnect/__init__.py
winConnect/__meta__.py
winConnect/errors.py
winConnect/exceptions.py
winConnect/utils.py
winconnect-0.9.3.dist-info/LICENSE
winconnect-0.9.3.dist-info/METADATA
winconnect-0.9.3.dist-info/WHEEL
winconnect-0.9.3.dist-info/top_level.txt
winconnect-0.9.3.dist-info/RECORD
